setup.py
zyutil/__init__.py
zyutil/assembly.py
zyutil/common.py
zyutil/daemon.py
zyutil/db_pool.py
zyutil/decorator.py
zyutil/http.py
zyutil/log.py
zyutil/logbase.py
zyutil/mem_buffer.py
zyutil/options.py
zyutil/test.py
zyutil/time_dedup_buffer.py
zyutil.egg-info/PKG-INFO
zyutil.egg-info/SOURCES.txt
zyutil.egg-info/dependency_links.txt
zyutil.egg-info/top_level.txt
zyutil/hashkit/__init__.py
zyutil/hashkit/consistent_hash.py
zyutil/lib/__init__.py
zyutil/lib/tornado/__init__.py
zyutil/lib/tornado/escape.py
zyutil/lib/tornado/options.py