Metadata-Version: 1.0
Name: zyutil
Version: 1.1.3
Summary: pyutil is a set of tools collection for python programming
Home-page: https://github.com/bufferx/pyutil
Author: Zhang ZY
Author-email: idup2x@gmail.com
License: http://www.apache.org/licenses/LICENSE-2.0
Platform: UNKNOWN
